homeassistant_enocean/__init__.py
homeassistant_enocean/address.py
homeassistant_enocean/device_type.py
homeassistant_enocean/eep.py
homeassistant_enocean/entity_id.py
homeassistant_enocean/entity_properties.py
homeassistant_enocean/gateway.py
homeassistant_enocean/serialcommunicator.py
homeassistant_enocean/types.py
homeassistant_enocean/device_factories/a502xx_factory.py
homeassistant_enocean/device_factories/a504xx_factory.py
homeassistant_enocean/device_factories/a50601_factory.py
homeassistant_enocean/device_factories/a50703_factory.py
homeassistant_enocean/device_factories/a50801_factory.py
homeassistant_enocean/device_factories/a53808_factory.py
homeassistant_enocean/device_factories/d201xx_factory.py
homeassistant_enocean/device_factories/d20500_factory.py
homeassistant_enocean/device_factories/device_factory.py
homeassistant_enocean/device_factories/f602xx_factory.py
homeassistant_enocean/devices/a502xx_device.py
homeassistant_enocean/devices/a504xx_device.py
homeassistant_enocean/devices/a50601_device.py
homeassistant_enocean/devices/a50703_device.py
homeassistant_enocean/devices/a50801_device.py
homeassistant_enocean/devices/a53808_device.py
homeassistant_enocean/devices/d201xx_device.py
homeassistant_enocean/devices/d20500_device.py
homeassistant_enocean/devices/device.py
homeassistant_enocean/devices/f602xx_device.py
homeassistant_enocean/devices/gateway_device.py
homeassistant_enocean-0.0.9.dist-info/licenses/LICENSE
homeassistant_enocean-0.0.9.dist-info/METADATA
homeassistant_enocean-0.0.9.dist-info/WHEEL
homeassistant_enocean-0.0.9.dist-info/top_level.txt
homeassistant_enocean-0.0.9.dist-info/RECORD
