Metadata-Version: 2.4
Name: homeassistant_enocean
Version: 0.0.9
Summary: A wrapper library to integrate EnOcean into Home Assistant
Author-email: Henning Kerstan <mail@henningkerstan.de>
License-Expression: Apache-2.0
Project-URL: Homepage, https://github.com/henningkerstan/homeassistant_enocean
Project-URL: Issues, https://github.com/henningkerstan/homeassistant_enocean/issues
Classifier: Programming Language :: Python :: 3
Classifier: Operating System :: OS Independent
Classifier: Intended Audience :: Developers
Classifier: Development Status :: 4 - Beta
Requires-Python: >=3.13
License-File: LICENSE
Requires-Dist: enocean4ha==0.71.0
Dynamic: license-file
